wavetorch/__init__.py
wavetorch/cell.py
wavetorch/geom.py
wavetorch/io.py
wavetorch/operators.py
wavetorch/plot.py
wavetorch/probe.py
wavetorch/rnn.py
wavetorch/source.py
wavetorch/train.py
wavetorch/utils.py
wavetorch-0.2.dist-info/LICENSE.md
wavetorch-0.2.dist-info/METADATA
wavetorch-0.2.dist-info/WHEEL
wavetorch-0.2.dist-info/top_level.txt
wavetorch-0.2.dist-info/RECORD
