Metadata-Version: 2.1
Name: wavetorch
Version: 0.2
Summary: Numerically solving and backpropagating through the wave equation using pytorch
Home-page: https://github.com/fancompute/wavetorch
Author: Ian Williamson, Tyler Hughes, Momchil Minkov, Shanhui Fan
Author-email: ian.williamson@ieee.org
License: MIT
Platform: UNKNOWN
